MANIFEST.in
README.rst
setup.py
espada/__init__.py
espada/main.py
espada.egg-info/PKG-INFO
espada.egg-info/SOURCES.txt
espada.egg-info/dependency_links.txt
espada.egg-info/entry_points.txt
espada.egg-info/not-zip-safe
espada.egg-info/requires.txt
espada.egg-info/top_level.txt
espada/templates/.DS_Store
espada/templates/__init__.py
espada/templates/app_cmake.txt
espada/templates/app_main.cpp
espada/templates/class_body.cpp
espada/templates/class_header.h
espada/templates/empty_src.cpp
espada/templates/gitkeep.txt
espada/templates/lib_cmake.txt
espada/templates/project_cmake.txt
espada/templates/single_app_cmake.txt
espada/templates/single_lib_cmake.txt
espada/templates/test_case.cpp
espada/templates/test_main.cpp
espada/templates/tests_cmake.txt