Metadata-Version: 1.0
Name: espada
Version: 2.1.2
Summary: C++ Project and Class Generator
Home-page: https://bitbucket.org/cajun_code/espada.py
Author: Allan Davis
Author-email: cajun.code@gmail.com
License: MIT
Platform: UNKNOWN
